README
setup.py
skipreq.py
nose_skipreq.egg-info/PKG-INFO
nose_skipreq.egg-info/SOURCES.txt
nose_skipreq.egg-info/dependency_links.txt
nose_skipreq.egg-info/entry_points.txt
nose_skipreq.egg-info/not-zip-safe
nose_skipreq.egg-info/top_level.txt