Metadata-Version: 1.0
Name: nose-skipreq
Version: 2.0
Summary: nose plugin that will skip Google API RequestError exceptions.
Home-page: https://github.com/tdavis/nose-skipreq
Author: Tom Davis
Author-email: tom@recursivedream.com
License: BSD License
Keywords: nose nosetest skip RequestError
Platform: UNKNOWN
Classifier: Development Status :: 5 - Production/Stable
Classifier: Intended Audience :: Developers
Classifier: License :: OSI Approved :: BSD License
Classifier: Operating System :: OS Independent
Classifier: Programming Language :: Python
Classifier: Programming Language :: Python :: 2.4
Classifier: Programming Language :: Python :: 2.5
Classifier: Programming Language :: Python :: 2.6
Classifier: Programming Language :: Python :: 2.7
Classifier: Topic :: Software Development :: Testing
